rich_toolbox-0.1.0.dist-info/licenses/LICENSE
rich_utils/__init__.py
rich_utils/config.py
rich_utils/enums.py
rich_utils/handler.py
rich_utils/core/__init__.py
rich_utils/core/base_handler.py
rich_utils/core/color_gradients.py
rich_utils/core/dashboard.py
rich_utils/core/layout.py
rich_utils/core/logger.py
rich_utils/core/printer.py
rich_utils/core/progress.py
rich_utils/core/rotate_log.py
rich_utils/core/spinner.py
rich_utils/core/stats.py
rich_utils/core/syntax_highlighting.py
rich_utils/core/table.py
rich_utils/core/timer.py
rich_utils/utils/__init__.py
rich_utils/utils/color.py
rich_utils/utils/file.py
rich_utils/utils/formatting.py
rich_utils/utils/math.py
rich_toolbox-0.1.0.dist-info/METADATA
rich_toolbox-0.1.0.dist-info/WHEEL
rich_toolbox-0.1.0.dist-info/top_level.txt
rich_toolbox-0.1.0.dist-info/RECORD
