Metadata-Version: 2.4
Name: rich-toolbox
Version: 0.1.0
Summary: A generic APIView base class for FastAPI with Tortoise ORM
Home-page: https://github.com/fzf54122/rich-utils
Author: fzf
Classifier: Programming Language :: Python :: 3.12
Classifier: License :: OSI Approved :: MIT License
Classifier: Operating System :: OS Independent
License-File: LICENSE
Requires-Dist: rich
Requires-Dist: watchfiles
Dynamic: author
Dynamic: classifier
Dynamic: description
Dynamic: description-content-type
Dynamic: home-page
Dynamic: license-file
Dynamic: requires-dist
Dynamic: summary
